pygafro/singlemanipulatormotorcost.py
pygafro/manipulator.py
pygafro/singlemanipulatordualtarget.py
pygafro/__init__.py
pygafro/innerproductcayleytable.py
pygafro/singlemanipulatortarget.py
pygafro/utils.py
pygafro/multivector.py
pygafro/outerproductcayleytable.py
pygafro/geometricproductcayleytable.py
pygafro/_pygafro.so
pygafro/mv_combinations.py
pygafro/assets/robots/anymal/anymal.yaml
pygafro/assets/robots/ufactory/lite6/lite6.yaml
pygafro/assets/robots/robotiq/3fGripper/robotiq-3f-gripper.yaml
pygafro/assets/robots/leap_hand/leap_hand.yaml
pygafro/assets/robots/kuka/iiwa7/iiwa7.yaml
pygafro/assets/robots/kuka/iiwa14/iiwa14.yaml
pygafro/assets/robots/panda/panda.yaml
pygafro/assets/robots/unitree/g1/g1.yaml
pygafro/assets/robots/ur5/ur5.yaml
pygafro/assets/robots/planar/3dof.yaml
pygafro/assets/robots/anymal_c/anymal_c.yaml
pygafro/assets/robots/atlas/atlas.yaml
pygafro-1.3.2.dist-info/RECORD
pygafro-1.3.2.dist-info/WHEEL
pygafro-1.3.2.dist-info/METADATA
