Metadata-Version: 2.2
Name: pygafro
Version: 1.3.2
Summary: Geometric algebra tools targeted towards robotics applications
Author-Email: Philip Abbet <philip.abbet@idiap.ch>, Tobias Loew <tobias.loew@idiap.ch>
Classifier: Development Status :: 5 - Production/Stable
Classifier: License :: OSI Approved :: Mozilla Public License 2.0 (MPL 2.0)
Classifier: Programming Language :: Python :: 3 :: Only
Classifier: Programming Language :: Python :: 3.8
Classifier: Programming Language :: Python :: 3.9
Classifier: Programming Language :: Python :: 3.10
Classifier: Programming Language :: Python :: 3.11
Classifier: Programming Language :: Python :: 3.12
Classifier: Programming Language :: Python :: 3.13
Requires-Python: >=3.8
Requires-Dist: numpy>=1.23.0
Provides-Extra: assets
Requires-Dist: pygafro-assets; extra == "assets"
